setup.py
functest/__init__.py
functest/bin.py
functest/collector.py
functest/formatter.py
functest/frame.py
functest/global_settings.py
functest/reports.py
functest/runner.py
functest.egg-info/PKG-INFO
functest.egg-info/SOURCES.txt
functest.egg-info/dependency_links.txt
functest.egg-info/entry_points.txt
functest.egg-info/top_level.txt
scripts/build_and_release.py
scripts/functest
scripts/mikeals_b_and_r.py
tests/__init__.py
tests/test_failure.py
tests/test_functest.py
tests/test_reporting.py
tests/files/failures/test_fail.py
tests/files/reports/test_reports.py
tests/test_module/__init__.py
tests/test_module/test_sub.py